cstore/__init__.py
cstore/cstore-package.py
cstore_package-0.1.1.dist-info/METADATA
cstore_package-0.1.1.dist-info/WHEEL
cstore_package-0.1.1.dist-info/top_level.txt
cstore_package-0.1.1.dist-info/RECORD
