Metadata-Version: 2.4
Name: cstore-package
Version: 0.1.1
Summary: "Cliente para gerenciar bibliotecas C/C++ em um servidor remoto."
Home-page: https://github.com/AliceAX24/Cstore
Author: "Alice Catano"
Author-email: "alice.schifelbein.caetano@gmail.com"
Requires-Python: >=3.6
Dynamic: home-page
